gpu_optimize/__init__.py
gpu_optimize/mf.py
gpu_optimize/tests/__init__.py
gpu_optimize/tests/test_basic.py
gpu_optimize/tests/test_big.py
gpu_optimize/tests/test_debug.py
gpu_optimize/tests/test_not_square.py
gpu_optimize/tests/test_streams.py
gpu_optimize/tests/timing.py
gpu_optimize-2018.8.dist-info/METADATA
gpu_optimize-2018.8.dist-info/RECORD
gpu_optimize-2018.8.dist-info/WHEEL
gpu_optimize-2018.8.dist-info/top_level.txt
