Metadata-Version: 2.1
Name: gpu-optimize
Version: 2018.8
Summary: Drop-in replacement functions that run on NVIDIA GPUs, parallelized for speed
Home-page: https://github.com/Jackmastr/gpu-optimize.git
Author: Jackson Sipple
License: UNKNOWN
Platform: UNKNOWN
Classifier: Programming Language :: Python :: 2
Classifier: Operating System :: OS Independent
